AUTHORS.md
LICENSE.md
MANIFEST.in
README.md
setup.py
quintet/__init__.py
quintet/admin.py
quintet/models.py
quintet/urls.py
quintet.egg-info/PKG-INFO
quintet.egg-info/SOURCES.txt
quintet.egg-info/dependency_links.txt
quintet.egg-info/not-zip-safe
quintet.egg-info/requires.txt
quintet.egg-info/top_level.txt
quintet/backend/__init__.py
quintet/backend/forms.py
quintet/backend/urls.py
quintet/backend/views.py
quintet/blog/__init__.py
quintet/blog/urls.py
quintet/blog/views.py
quintet/static/.DS_Store
quintet/static/css/quintet.css
quintet/static/img/default.jpg
quintet/static/js/jquery.selection.min.js
quintet/static/js/murmurhash3.js
quintet/templates/.DS_Store
quintet/templates/article.html
quintet/templates/list.html
quintet/templates/page.html
quintet/templates/post.html
quintet/templates/quintet/.DS_Store
quintet/templates/quintet/add_user.html
quintet/templates/quintet/comments.html
quintet/templates/quintet/dashboard.html
quintet/templates/quintet/login.html
quintet/templates/quintet/page.html
quintet/templates/quintet/page_list.html
quintet/templates/quintet/post.html
quintet/templates/quintet/post_list.html
quintet/templates/quintet/post_read_only.html
quintet/templates/quintet/section_list.html
quintet/templates/quintet/settings.html
quintet/templates/quintet/settings_delete.html
quintet/templates/quintet/settings_password.html
quintet/templates/quintet/settings_permissions.html
quintet/templates/quintet/user_list.html
quintet/templates/quintet/misc/user_photo.html
quintet/templates/quintet/modals/add_contributor.html
quintet/templates/quintet/modals/add_reviewer.html
quintet/templates/quintet/modals/add_section.html
quintet/templates/quintet/modals/change_password.html
quintet/templates/quintet/modals/change_photo.html
quintet/templates/quintet/modals/confirm_archive.html
quintet/templates/quintet/modals/confirm_delete.html
quintet/templates/quintet/modals/edit_contributor.html
quintet/templates/quintet/toolbars/archive_toolbar.html
quintet/templates/quintet/toolbars/draft_toolbar.html
quintet/templates/quintet/toolbars/hidden_toolbar.html
quintet/templates/quintet/toolbars/publish_toolbar.html
